prompt_collapse/__init__.py
prompt_collapse/common/__init__.py
prompt_collapse/common/distributions/__init__.py
prompt_collapse/common/distributions/distribution.py
prompt_collapse/common/distributions/weighted.py
prompt_collapse/common/protocols/__init__.py
prompt_collapse/common/protocols/evaluatable.py
prompt_collapse/common/protocols/loadable.py
prompt_collapse/common/quota/__init__.py
prompt_collapse/common/quota/fixed.py
prompt_collapse/common/quota/quota.py
prompt_collapse/common/quota/range.py
prompt_collapse/common/quota/registry.py
prompt_collapse/common/registry.py
prompt_collapse/common/transformations/__init__.py
prompt_collapse/common/transformations/constant.py
prompt_collapse/common/transformations/identity.py
prompt_collapse/common/transformations/lookup.py
prompt_collapse/common/transformations/match.py
prompt_collapse/common/transformations/random_int.py
prompt_collapse/common/transformations/random_value.py
prompt_collapse/common/transformations/registry.py
prompt_collapse/common/transformations/replace_none.py
prompt_collapse/common/transformations/sequence.py
prompt_collapse/common/transformations/transformation.py
prompt_collapse/common/utils.py
prompt_collapse/component.py
prompt_collapse/content/__init__.py
prompt_collapse/content/constant.py
prompt_collapse/content/content.py
prompt_collapse/content/registry.py
prompt_collapse/content/sequence.py
prompt_collapse/content/some_of.py
prompt_collapse/declaration/__init__.py
prompt_collapse/declaration/declaration.py
prompt_collapse/declaration/decrement.py
prompt_collapse/declaration/emit.py
prompt_collapse/declaration/emit_if_none.py
prompt_collapse/declaration/increment.py
prompt_collapse/declaration/overwrite.py
prompt_collapse/declaration/registry.py
prompt_collapse/parameters/__init__.py
prompt_collapse/parameters/parameter.py
prompt_collapse/repository.py
prompt_collapse/requirement/__init__.py
prompt_collapse/requirement/all_of.py
prompt_collapse/requirement/equals.py
prompt_collapse-0.1.3.5.dist-info/LICENSE
prompt_collapse-0.1.3.5.dist-info/METADATA
prompt_collapse-0.1.3.5.dist-info/WHEEL
prompt_collapse-0.1.3.5.dist-info/RECORD
