Metadata-Version: 2.1
Name: prompt_collapse
Version: 0.1.3.5
Summary: A prompt generation system that manages relationships between prompt components to maintain logical consistency
Home-page: https://github.com/kraglik/prompt_collapse
License: MIT
Keywords: prompt,generation,ai,stable-diffusion,comfyui
Author: kraglik
Author-email: kraglik.i.d@gmail.com
Requires-Python: >=3.10
Classifier: License :: OSI Approved :: MIT License
Classifier: Programming Language :: Python :: 3
Classifier: Programming Language :: Python :: 3.10
Classifier: Programming Language :: Python :: 3.11
Classifier: Programming Language :: Python :: 3.12
Requires-Dist: pyyaml (>=6.0.2)
Project-URL: Documentation, https://github.com/kraglik/prompt_collapse
Project-URL: Repository, https://github.com/kraglik/prompt_collapse
